main.py
hellopackage_meharik-0.2.1.dist-info/licenses/LICENSE
hellopackage_meharik-0.2.1.dist-info/METADATA
hellopackage_meharik-0.2.1.dist-info/WHEEL
hellopackage_meharik-0.2.1.dist-info/top_level.txt
hellopackage_meharik-0.2.1.dist-info/RECORD
