Metadata-Version: 2.4
Name: hellopackage-meharik
Version: 0.2.1
Summary: Practicing of package publishing and shiping
Author-email: MEHARI KIROS <meharik2001@gmail.com>
Classifier: Programming Language :: Python :: 3
Classifier: License :: OSI Approved :: GNU General Public License v3 (GPLv3)
Classifier: Operating System :: OS Independent
Requires-Python: >=3.12
License-File: LICENSE
Dynamic: license-file
